setup.py
nozdormu/__init__.py
nozdormu/batch.py
nozdormu/loader.py
nozdormu/main.py
nozdormu/runner.py
nozdormu/suite.py
nozdormu/util.py
nozdormu.egg-info/PKG-INFO
nozdormu.egg-info/SOURCES.txt
nozdormu.egg-info/dependency_links.txt
nozdormu.egg-info/not-zip-safe
nozdormu.egg-info/requires.txt
nozdormu.egg-info/top_level.txt